sdanalysis/StepSize.py
sdanalysis/__init__.py
sdanalysis/_order.cpp
sdanalysis/_order.cpython-36m-darwin.so
sdanalysis/_order.pyx
sdanalysis/dynamics.py
sdanalysis/frame.py
sdanalysis/main.py
sdanalysis/math_util.c
sdanalysis/math_util.cpython-36m-darwin.so
sdanalysis/math_util.pxd
sdanalysis/math_util.pyx
sdanalysis/molecules.py
sdanalysis/order.py
sdanalysis/params.py
sdanalysis/read.py
sdanalysis/relaxation.py
sdanalysis/run_analysis.py
sdanalysis/thermodynamics.py
sdanalysis/util.py
sdanalysis/version.py
sdanalysis/figures/__init__.py
sdanalysis/figures/configuration.py
sdanalysis/figures/interactive_config.py
sdanalysis/figures/thermodynamics.py
sdanalysis/figures/trimer.py
sdanalysis/figures/trimer.ts
sdanalysis/models/dt-Trimer-model.pkl
sdanalysis/models/knn-Trimer-model.pkl
sdanalysis-0.5.4.dist-info/LICENSE.txt
sdanalysis-0.5.4.dist-info/METADATA
sdanalysis-0.5.4.dist-info/RECORD
sdanalysis-0.5.4.dist-info/WHEEL
sdanalysis-0.5.4.dist-info/entry_points.txt
sdanalysis-0.5.4.dist-info/top_level.txt
