Metadata-Version: 2.1
Name: sdanalysis
Version: 0.5.4
Summary: Statistical dynamics analysis of molecular dynamics trajectories.
Home-page: https://github.com/malramsay64/statdyn-analysis
Author: Malcolm Ramsay
Author-email: malramsay64@gmail.com
License: UNKNOWN
Platform: UNKNOWN
Classifier: Development Status :: 3 - Alpha
Classifier: Environment :: Console
Classifier: Intended Audience :: Developers
Classifier: Intended Audience :: Science/Research
Classifier: License :: OSI Approved :: MIT License
Classifier: Operating System :: MacOS :: MacOS X
Classifier: Operating System :: POSIX :: Linux
Classifier: Programming Language :: Python :: 3
Classifier: Programming Language :: Python :: 3.6
Requires-Python: >=3.6
Provides-Extra: tests
Provides-Extra: dev
Provides-Extra: docs
Requires-Dist: numpy (>=1.13)
Requires-Dist: scipy (>=1.0)
Requires-Dist: scikit-learn (==0.19.0)
Requires-Dist: pandas
Requires-Dist: tables
Requires-Dist: bokeh (>=0.12.11)
Requires-Dist: matplotlib (>=2.1)
Requires-Dist: gsd (>=1.3.0)
Requires-Dist: ruamel.yaml
Requires-Dist: hsluv
Requires-Dist: attrs
Provides-Extra: dev
Requires-Dist: pytest; extra == 'dev'
Requires-Dist: pylint; extra == 'dev'
Requires-Dist: numpy-quaternion; extra == 'dev'
Requires-Dist: hypothesis; extra == 'dev'
Requires-Dist: coverage; extra == 'dev'
Requires-Dist: mypy; extra == 'dev'
Requires-Dist: pytest-mypy; extra == 'dev'
Requires-Dist: pytest-pylint; extra == 'dev'
Requires-Dist: pytest-cov; extra == 'dev'
Requires-Dist: pytest-lazy-fixture; extra == 'dev'
Provides-Extra: docs
Provides-Extra: tests
Requires-Dist: pytest; extra == 'tests'
Requires-Dist: pylint; extra == 'tests'
Requires-Dist: numpy-quaternion; extra == 'tests'
Requires-Dist: hypothesis; extra == 'tests'
Requires-Dist: coverage; extra == 'tests'
Requires-Dist: mypy; extra == 'tests'
Requires-Dist: pytest-mypy; extra == 'tests'
Requires-Dist: pytest-pylint; extra == 'tests'
Requires-Dist: pytest-cov; extra == 'tests'
Requires-Dist: pytest-lazy-fixture; extra == 'tests'
